pd_pump/__init__.py
pd_pump/controller.py
pd_pump/parameters.json
pd_pump/parameters.py
pd_pump/pump.py
py_pd_stepper_pump-0.1.0.dist-info/METADATA
py_pd_stepper_pump-0.1.0.dist-info/WHEEL
py_pd_stepper_pump-0.1.0.dist-info/RECORD
